aistudio/__init__.py
aistudio/studio.py
aistudio/utils.py
aistudio-0.0.1.dist-info/METADATA
aistudio-0.0.1.dist-info/WHEEL
aistudio-0.0.1.dist-info/top_level.txt
aistudio-0.0.1.dist-info/RECORD
