Metadata-Version: 2.1
Name: aistudio
Version: 0.0.1
Summary: A Simple program to Handle AI Research Needs
Home-page: https://github.com/yashbonde/aistudio
Author: Yash Bonde
Author-email: bonde.yash97@gmail.com
License: UNKNOWN
Platform: UNKNOWN
Classifier: Programming Language :: Python :: 3
Classifier: License :: OSI Approved :: MIT License
Classifier: Operating System :: OS Independent
